omega_format/__init__.py
omega_format/cli.py
omega_format/meta_data.py
omega_format/perception_recording.py
omega_format/reference_recording.py
omega_format/reference_resolving.py
omega_format/settings.py
omega_format/converters/__init__.py
omega_format/converters/from_level_x_like.py
omega_format/converters/from_asam_opendrive/__init__.py
omega_format/converters/from_asam_opendrive/eulerspiral.py
omega_format/converters/from_asam_opendrive/from_asam_opendrive.py
omega_format/converters/from_asam_opendrive/opendriveconverter/__init__.py
omega_format/converters/from_asam_opendrive/opendriveconverter/converter.py
omega_format/converters/from_asam_opendrive/opendriveconverter/logger.py
omega_format/converters/from_asam_opendrive/opendriveconverter/elements/__init__.py
omega_format/converters/from_asam_opendrive/opendriveconverter/elements/boundary.py
omega_format/converters/from_asam_opendrive/opendriveconverter/elements/centerLinePoints.py
omega_format/converters/from_asam_opendrive/opendriveconverter/elements/junction.py
omega_format/converters/from_asam_opendrive/opendriveconverter/elements/lane.py
omega_format/converters/from_asam_opendrive/opendriveconverter/elements/mapping.py
omega_format/converters/from_asam_opendrive/opendriveconverter/elements/objects.py
omega_format/converters/from_asam_opendrive/opendriveconverter/elements/objectsTunnelBridge.py
omega_format/converters/from_asam_opendrive/opendriveconverter/elements/polyline.py
omega_format/converters/from_asam_opendrive/opendriveconverter/elements/road.py
omega_format/converters/from_asam_opendrive/opendriveconverter/elements/roads.py
omega_format/converters/from_asam_opendrive/opendriveconverter/elements/signals.py
omega_format/converters/from_asam_opendrive/opendriveparser/__init__.py
omega_format/converters/from_asam_opendrive/opendriveparser/parser.py
omega_format/converters/from_asam_opendrive/opendriveparser/elements/__init__.py
omega_format-4.4.1.dist-info/LICENSE
omega_format-4.4.1.dist-info/LICENSES_OF_REQUIREMENTS.md
omega_format-4.4.1.dist-info/METADATA
omega_format-4.4.1.dist-info/WHEEL
omega_format-4.4.1.dist-info/entry_points.txt
omega_format-4.4.1.dist-info/top_level.txt
omega_format-4.4.1.dist-info/RECORD
