Metadata-Version: 2.2
Name: omega_format
Version: 4.4.1
Summary: OMEGAFormat Library (read/write/visualize): A Comprehensive Format of Traffic Recordings for Scenario Extraction
Author-email: ika - RWTH Aachen <michael.schuldes@ika.rwth-aachen.de>
License: MIT
Keywords: automated driving,traffic,scenario
Classifier: Programming Language :: Python :: 3
Classifier: Programming Language :: Python :: 3.9
Classifier: Programming Language :: Python :: 3.10
Classifier: Programming Language :: Python :: 3.11
Classifier: Programming Language :: Python :: 3.12
Classifier: License :: OSI Approved :: MIT License
Classifier: Operating System :: OS Independent
Requires-Python: >=3.9
License-File: LICENSE
License-File: LICENSES_OF_REQUIREMENTS.md
Requires-Dist: numpy
Requires-Dist: h5py
Requires-Dist: tqdm
Requires-Dist: typer
Requires-Dist: xarray
Requires-Dist: scipy
Requires-Dist: pydantic>=2
Requires-Dist: pydantic-settings
Requires-Dist: pydantic-numpy
Requires-Dist: parse
Requires-Dist: shapely
Requires-Dist: pyproj
Requires-Dist: lxml
Provides-Extra: visualization
Requires-Dist: pyqtgraph; extra == "visualization"
Requires-Dist: pyqt5; extra == "visualization"
Provides-Extra: doc
Requires-Dist: pdoc3; extra == "doc"
Provides-Extra: test
Requires-Dist: ruff; extra == "test"
Requires-Dist: pytest; extra == "test"
Requires-Dist: pytest-sugar; extra == "test"
Requires-Dist: pytest-env; extra == "test"
Requires-Dist: pytest-cov; extra == "test"
Requires-Dist: pytest-progress; extra == "test"
Requires-Dist: nbval; extra == "test"
